network3_perseus/__init__.py
network3_perseus/network3_perseus.py
network3_perseus/script.py
network3_perseus/templates/intended_config.j2
network3_perseus-0.1.96.dist-info/entry_points.txt
network3_perseus-0.1.96.dist-info/LICENSE
network3_perseus-0.1.96.dist-info/WHEEL
network3_perseus-0.1.96.dist-info/METADATA
network3_perseus-0.1.96.dist-info/RECORD
