Metadata-Version: 2.1
Name: network3-perseus
Version: 0.1.96
Summary: Generating and applying intent-based Network configuration from Hedera
Author: John Capobianco
Author-email: ptcapo@gmail.com
Requires-Python: >=3.8,<4.0
Classifier: Programming Language :: Python :: 3
Classifier: Programming Language :: Python :: 3.10
Classifier: Programming Language :: Python :: 3.8
Classifier: Programming Language :: Python :: 3.9
Requires-Dist: Jinja2 (>=3.1.2,<4.0.0)
Requires-Dist: PyYAML (>=6.0,<7.0)
Requires-Dist: hedera-sdk-py (>=2.15.0,<3.0.0)
Requires-Dist: requests (>=2.28.1,<3.0.0)
